grscheller_courses_distributions/__init__.py
grscheller_courses_distributions/binomial.py
grscheller_courses_distributions/distribution.py
grscheller_courses_distributions/gaussian.py
grscheller_courses_distributions/py.typed
grscheller_courses_distributions-0.1.1.dist-info/LICENSE
grscheller_courses_distributions-0.1.1.dist-info/WHEEL
grscheller_courses_distributions-0.1.1.dist-info/METADATA
grscheller_courses_distributions-0.1.1.dist-info/RECORD
