Metadata-Version: 2.1
Name: grscheller-courses-distributions
Version: 0.1.1
Summary: Module of classes representing various probability distributions
Keywords: udacity,probability,distribution,gaussian
Author-email: "Geoffrey R. Scheller" <geoffrey@scheller.com>
Requires-Python: >=3.10.13
Classifier: Development Status :: 3 - Alpha
Classifier: Programming Language :: Python :: 3
Classifier: Operating System :: OS Independent
Classifier: License :: OSI Approved :: Apache Software License
Requires-Dist: pytest >=7.4 ; extra == "test"
Project-URL: Documentation, https://grscheller.github.io/courses-distributions
Project-URL: Source, https://github.com/grscheller/courses-distributions
Provides-Extra: test
